unique_variable
